changelog_keeper/__init__.py
changelog_keeper/app.py
changelog_keeper/cli.py
changelog_keeper/keeper.py
changelog_keeper/model.py
changelog_keeper/parser.py
changelog_keeper-1.0.0.dist-info/LICENSE
changelog_keeper-1.0.0.dist-info/METADATA
changelog_keeper-1.0.0.dist-info/WHEEL
changelog_keeper-1.0.0.dist-info/entry_points.txt
changelog_keeper-1.0.0.dist-info/top_level.txt
changelog_keeper-1.0.0.dist-info/RECORD
