Metadata-Version: 2.1
Name: changelog-keeper
Version: 1.0.0
Summary: Command line utility for keeping your changelog tidy
Author: Jacek Lewański
License: MIT License
Project-URL: Homepage, https://github.com/nullJaX/changelog-keeper
Project-URL: Repository, https://github.com/nullJaX/changelog-keeper.git
Keywords: changelog,changelog-generator,changelog-formatter,changelog-parser,keep-a-changelog
Classifier: Development Status :: 5 - Production/Stable
Classifier: Environment :: Console
Classifier: Intended Audience :: Developers
Classifier: License :: OSI Approved :: MIT License
Classifier: Operating System :: POSIX
Classifier: Operating System :: POSIX :: Linux
Classifier: Programming Language :: Python :: 3.7
Classifier: Programming Language :: Python :: 3.8
Classifier: Programming Language :: Python :: 3.9
Classifier: Programming Language :: Python :: 3.10
Classifier: Topic :: Documentation
Classifier: Topic :: Software Development :: Version Control
Classifier: Topic :: Text Processing
Classifier: Topic :: Text Processing :: Markup :: Markdown
Classifier: Topic :: Utilities
Classifier: Typing :: Typed
Requires-Python: >=3.7
License-File: LICENSE
